asvmaker/__init__.py
asvmaker/__main__.py
asvmaker/database.py
asvmaker/edit.py
asvmaker/export.py
asvmaker/filter.py
asvmaker/lineage.py
asvmaker/merge.py
asvmaker/pcr.py
asvmaker/stats.py
asvmaker/utils.py
ASVmaker-0.0.2.dist-info/LICENSE.txt
ASVmaker-0.0.2.dist-info/METADATA
ASVmaker-0.0.2.dist-info/WHEEL
ASVmaker-0.0.2.dist-info/top_level.txt
ASVmaker-0.0.2.dist-info/RECORD
