Metadata-Version: 2.1
Name: ASVmaker
Version: 0.0.2
Summary: ASVmaker: A new tool to improve taxonomic identifications for amplicon sequencing data
Author: Clement PLESSIS
Project-URL: Homepage, https://github.com/cplessis/ASVmaker
Project-URL: Bug Tracker, https://github.com/cplessis/ASVmaker/issues
Classifier: Programming Language :: Python :: 3
Classifier: License :: OSI Approved :: MIT License
Classifier: Operating System :: OS Independent
Requires-Python: >=3.7
License-File: LICENSE.txt
Requires-Dist: pydna ==3.1.3
Requires-Dist: progress ==1.5
Requires-Dist: Bio ==1.0.2
Requires-Dist: argparse ==1.4.0
